XOGoogle/__init__.py
XOGoogle/__version__.py
XOGoogle/xo_google.py
XOGoogle/core/__init__.py
XOGoogle/core/input.py
XOGoogle/core/scraper.py
XOGoogle/core/settings.py
XOGoogle-1.1.3.dist-info/LICENSE
XOGoogle-1.1.3.dist-info/METADATA
XOGoogle-1.1.3.dist-info/WHEEL
XOGoogle-1.1.3.dist-info/entry_points.txt
XOGoogle-1.1.3.dist-info/top_level.txt
XOGoogle-1.1.3.dist-info/RECORD
