Metadata-Version: 2.1
Name: XOGoogle
Version: 1.1.3
Summary: XOGoogle is a google bot that scraps google for keywords and returns all links
Home-page: https://strobes.co/
Author: Akhil Reni
Author-email: akhil@wesecureapp.com
License: GPLv3
Platform: UNKNOWN
Requires-Python: >=3.6
Requires-Dist: requests (==2.24.0)
Requires-Dist: bs4 (==0.0.1)
